{
    "$schema": "https://json-schema.org/draft/2020-12/schema",
    "$id": "UserExistsResponse.json",
    "type": "object",
    "properties": {
        "statusCode": {
            "type": "number",
            "const": 409,
            "description": "The status code."
        },
        "code": {
            "type": "string",
            "const": "user-exists"
        }
    },
    "required": [
        "statusCode",
        "code"
    ],
    "allOf": [
        {
            "$ref": "ApiError.json"
        }
    ],
    "description": "The user already exists"
}